README.md
setup.cfg
setup.py
easy_stopwatch/__init__.py
easy_stopwatch.egg-info/PKG-INFO
easy_stopwatch.egg-info/SOURCES.txt
easy_stopwatch.egg-info/dependency_links.txt
easy_stopwatch.egg-info/top_level.txt